polyglot_ffi/__init__.py
polyglot_ffi/__main__.py
polyglot_ffi/cli/__init__.py
polyglot_ffi/cli/main.py
polyglot_ffi/commands/__init__.py
polyglot_ffi/commands/check.py
polyglot_ffi/commands/clean.py
polyglot_ffi/commands/generate.py
polyglot_ffi/commands/init.py
polyglot_ffi/commands/watch.py
polyglot_ffi/core/__init__.py
polyglot_ffi/core/config.py
polyglot_ffi/generators/__init__.py
polyglot_ffi/generators/c_stubs_gen.py
polyglot_ffi/generators/ctypes_gen.py
polyglot_ffi/generators/dune_gen.py
polyglot_ffi/generators/python_gen.py
polyglot_ffi/ir/__init__.py
polyglot_ffi/ir/types.py
polyglot_ffi/parsers/__init__.py
polyglot_ffi/parsers/ocaml.py
polyglot_ffi/type_system/__init__.py
polyglot_ffi/type_system/builtin.py
polyglot_ffi/type_system/registry.py
polyglot_ffi/utils/__init__.py
polyglot_ffi/utils/errors.py
polyglot_ffi/utils/naming.py
polyglot_ffi-0.5.2.dist-info/licenses/LICENSE
polyglot_ffi-0.5.2.dist-info/METADATA
polyglot_ffi-0.5.2.dist-info/WHEEL
polyglot_ffi-0.5.2.dist-info/entry_points.txt
polyglot_ffi-0.5.2.dist-info/top_level.txt
polyglot_ffi-0.5.2.dist-info/RECORD
