Metadata-Version: 2.4
Name: polyglot-ffi
Version: 0.5.2
Summary: Automatic FFI bindings generator for polyglot projects
Author-email: Chizaram Chibueze <chizy@chizyhub.com>
License: MIT
Project-URL: Homepage, https://github.com/chizy7/polyglot-ffi
Project-URL: Documentation, https://polyglotffi.com/
Project-URL: Repository, https://github.com/chizy7/polyglot-ffi
Project-URL: Issues, https://github.com/chizy7/polyglot-ffi/issues
Project-URL: Changelog, https://github.com/chizy7/polyglot-ffi/blob/master/CHANGELOG.md
Keywords: ffi,bindings,ocaml,python,rust,ctypes,polyglot
Classifier: Development Status :: 3 - Alpha
Classifier: Intended Audience :: Developers
Classifier: Programming Language :: Python :: 3
Classifier: Programming Language :: Python :: 3.8
Classifier: Programming Language :: Python :: 3.9
Classifier: Programming Language :: Python :: 3.10
Classifier: Programming Language :: Python :: 3.11
Classifier: Programming Language :: Python :: 3.12
Classifier: Topic :: Software Development :: Code Generators
Classifier: Topic :: Software Development :: Libraries
Requires-Python: >=3.8
License-File: LICENSE
Requires-Dist: click>=8.1.0
Requires-Dist: rich>=13.0.0
Requires-Dist: tomli>=2.0.0; python_version < "3.11"
Requires-Dist: pydantic>=2.0.0
Requires-Dist: watchdog>=3.0.0
Provides-Extra: dev
Requires-Dist: pytest>=7.0.0; extra == "dev"
Requires-Dist: pytest-cov>=4.0.0; extra == "dev"
Requires-Dist: pytest-mock>=3.10.0; extra == "dev"
Requires-Dist: black>=23.0.0; extra == "dev"
Requires-Dist: ruff>=0.1.0; extra == "dev"
Requires-Dist: mypy>=1.0.0; extra == "dev"
Dynamic: license-file
